iso19794/FAC.py
iso19794/FIR.py
iso19794/__init__.py
iso19794-0.1.0.dist-info/AUTHORS.rst
iso19794-0.1.0.dist-info/LICENSE
iso19794-0.1.0.dist-info/METADATA
iso19794-0.1.0.dist-info/WHEEL
iso19794-0.1.0.dist-info/top_level.txt
iso19794-0.1.0.dist-info/RECORD
