Metadata-Version: 2.1
Name: iso19794
Version: 0.1.0
Summary: ISO-19794 Image format for Python
Home-page: https://github.com/idemia/python-iso19794
Author: Olivier Heurtier
Author-email: olivier.heurtier@idemia.com
License: CeCILL-C
Platform: UNKNOWN
Classifier: Development Status :: 4 - Beta
Classifier: Programming Language :: Python :: 3.6
Classifier: Programming Language :: Python :: 3.7
Classifier: Programming Language :: Python :: 3.8
Classifier: License :: CeCILL-C Free Software License Agreement (CECILL-C)
Classifier: Operating System :: OS Independent
Requires-Dist: setuptools
Requires-Dist: Pillow (>=5.0.0)
